cattrs_env/__init__.py
cattrs_env/py.typed
cattrs_env-1.0.4.dist-info/LICENSE
cattrs_env-1.0.4.dist-info/METADATA
cattrs_env-1.0.4.dist-info/WHEEL
cattrs_env-1.0.4.dist-info/top_level.txt
cattrs_env-1.0.4.dist-info/RECORD
