Metadata-Version: 2.1
Name: cattrs-env
Version: 1.0.4
Summary: A tool for parsing and validating env vars using cattrs
Author-email: Henry Jones <henryivesjones@gmail.com>
License: MIT
Project-URL: Homepage, https://github.com/henryivesjones/cattrs-env
Keywords: cattrs,envvar,environment variables,attrs,dataclasses
Classifier: Programming Language :: Python :: 3
Classifier: License :: OSI Approved :: MIT License
Classifier: Operating System :: OS Independent
Requires-Python: >=3.7
License-File: LICENSE
Requires-Dist: cattrs >=20
